{
    "type": "FeatureCollection",
    "name": "ShelterRouteJson",
    "features": [
        {
            "type": "Feature",
            "properties": {
                "id": 1,
                "ShltrRoute": "r1"
            },
            "geometry": {
                "type": "LineString",
                "coordinates": [
                    [100.1687579, 14.0521509],
                    [100.17024,  14.0327176],
                    [100.1697125, 14.0289196],
                    [100.1696276, 14.023189],
                    [100.1735581, 14.0233333],
                    [100.1737487, 14.0230177],
                    [100.1748443, 14.0178563],
                    [100.174829, 14.0172815],
                    [100.1750563, 14.0168809],
                    [100.2481627, 14.0076617],
                    [100.2489257, 14.0077789],
                    [100.2497964, 14.0083372],
                    [100.257867, 14.0153698],
                    [100.2580396, 14.0151873],
                    [100.257087, 14.0143995],
                    [100.2567168, 14.0135663],
                    [100.2567323, 14.0130034],
                    [100.260498, 14.0102485],
                    [100.2621559, 14.0085333],
                    [100.273467, 14.0007039],
                    [100.2736292, 14.0008967]
                ]
            }
        }
    ]
}